AUTHORS.rst
CHANGELOG.md
CONTRIBUTING.rst
LICENSE
MANIFEST.in
README.md
README.rst
setup.cfg
setup.py
versioneer.py
docs/Makefile
docs/authors.rst
docs/conf.py
docs/contributing.rst
docs/history.rst
docs/index.rst
docs/installation.rst
docs/make.bat
docs/readme.rst
docs/usage.rst
requirements/base.txt
requirements/dev.txt
requirements/test.txt
slurm_tui/__init__.py
slurm_tui/_version.py
slurm_tui/cli.py
slurm_tui/slurm_tui.py
slurm_tui.egg-info/PKG-INFO
slurm_tui.egg-info/SOURCES.txt
slurm_tui.egg-info/dependency_links.txt
slurm_tui.egg-info/entry_points.txt
slurm_tui.egg-info/not-zip-safe
slurm_tui.egg-info/requires.txt
slurm_tui.egg-info/top_level.txt
tests/__init__.py
tests/test_slurm_tui.py