Metadata-Version: 2.1
Name: slurm-tui
Version: 0.1.3
Summary: Slurm Text User Interface using the Slurm REST API in Python.
Home-page: https://github.com/holtgrewe/slurm_tui
Author: Manuel Holtgrewe
Author-email: manuel.holtgrewe@bih-charite.de
License: MIT license
Keywords: slurm
Platform: UNKNOWN
Classifier: Development Status :: 2 - Pre-Alpha
Classifier: Intended Audience :: Developers
Classifier: License :: OSI Approved :: MIT License
Classifier: Natural Language :: English
Classifier: Programming Language :: Python :: 3
Classifier: Programming Language :: Python :: 3.6
Classifier: Programming Language :: Python :: 3.7
Classifier: Programming Language :: Python :: 3.8
Requires-Python: >=3.6
License-File: LICENSE
License-File: AUTHORS.rst
